agent_sv288/__init__.py
agent_sv288/client.py
agent_sv288/exceptions.py
agent_sv288/settings.py
cc_sv288-1.0.7.dist-info/METADATA
cc_sv288-1.0.7.dist-info/WHEEL
cc_sv288-1.0.7.dist-info/top_level.txt
cc_sv288-1.0.7.dist-info/RECORD
