Metadata-Version: 2.1
Name: cc-sv288
Version: 1.0.7
Summary: Agent sv288
Home-page: https://github.com/cockreative/cc-sv288
Author: Cockreative
Author-email: contact@cockreative.com
License: UNKNOWN
Project-URL: Bug Tracker, https://github.com/cockreative/cc-sv288/issues
Platform: UNKNOWN
Classifier: Programming Language :: Python :: 3
Classifier: License :: OSI Approved :: MIT License
Classifier: Operating System :: OS Independent
Requires-Python: >=3.8
Requires-Dist: beautifulsoup4
Requires-Dist: cc-agent-helper
